python_package_starter/__init__.py
python_package_starter/bar.py
python_package_starter/fizzbugzz.py
python_package_starter/foo.py
python_package_starter/welcome.py
python_package_starter-2.0.2.dist-info/LICENSE
python_package_starter-2.0.2.dist-info/METADATA
python_package_starter-2.0.2.dist-info/WHEEL
python_package_starter-2.0.2.dist-info/RECORD
