Metadata-Version: 2.1
Name: python-package-starter
Version: 2.0.2
Summary: python-package-starter
Author: ablil
Requires-Python: >=3.12,<4.0
Classifier: Programming Language :: Python :: 3
Classifier: Programming Language :: Python :: 3.12
Classifier: Programming Language :: Python :: 3.13
Requires-Dist: requests (>=2.32.3,<3.0.0)
